LICENSE
MANIFEST.in
README.rst
requirements.pip
setup.py
bin/excelsior
excelsior/__init__.py
excelsior.egg-info/PKG-INFO
excelsior.egg-info/SOURCES.txt
excelsior.egg-info/dependency_links.txt
excelsior.egg-info/requires.txt
excelsior.egg-info/top_level.txt